{
	"textures": [
		{
			"image": "character.png",
			"format": "RGBA8888",
			"size": {
				"w": 962,
				"h": 452
			},
			"scale": 1,
			"frames": [
				{
					"filename": "character.png",
					"rotated": false,
					"trimmed": false,
					"sourceSize": {
						"w": 464,
						"h": 180
					},
					"spriteSourceSize": {
						"x": 0,
						"y": 0,
						"w": 464,
						"h": 180
					},
					"frame": {
						"x": 1,
						"y": 1,
						"w": 464,
						"h": 180
					},
					"anchor": {
						"x": 0.5,
						"y": 0.5
					}
				},
				{
					"filename": "attack-left-2.png",
					"rotated": false,
					"trimmed": false,
					"sourceSize": {
						"w": 84,
						"h": 88
					},
					"spriteSourceSize": {
						"x": 0,
						"y": 0,
						"w": 84,
						"h": 88
					},
					"frame": {
						"x": 1,
						"y": 183,
						"w": 84,
						"h": 88
					},
					"anchor": {
						"x": 0.5,
						"y": 0.5
					}
				},
				{
					"filename": "attack-right-2.png",
					"rotated": false,
					"trimmed": false,
					"sourceSize": {
						"w": 80,
						"h": 84
					},
					"spriteSourceSize": {
						"x": 0,
						"y": 0,
						"w": 80,
						"h": 84
					},
					"frame": {
						"x": 467,
						"y": 1,
						"w": 80,
						"h": 84
					},
					"anchor": {
						"x": 0.5,
						"y": 0.5
					}
				},
				{
					"filename": "attack-down-3.png",
					"rotated": false,
					"trimmed": false,
					"sourceSize": {
						"w": 64,
						"h": 96
					},
					"spriteSourceSize": {
						"x": 0,
						"y": 0,
						"w": 64,
						"h": 96
					},
					"frame": {
						"x": 1,
						"y": 273,
						"w": 64,
						"h": 96
					},
					"anchor": {
						"x": 0.5,
						"y": 0.5
					}
				},
				{
					"filename": "attack-left-3.png",
					"rotated": false,
					"trimmed": false,
					"sourceSize": {
						"w": 72,
						"h": 88
					},
					"spriteSourceSize": {
						"x": 0,
						"y": 0,
						"w": 72,
						"h": 88
					},
					"frame": {
						"x": 87,
						"y": 183,
						"w": 72,
						"h": 88
					},
					"anchor": {
						"x": 0.5,
						"y": 0.5
					}
				},
				{
					"filename": "attack-down-4.png",
					"rotated": false,
					"trimmed": false,
					"sourceSize": {
						"w": 64,
						"h": 96
					},
					"spriteSourceSize": {
						"x": 0,
						"y": 0,
						"w": 64,
						"h": 96
					},
					"frame": {
						"x": 67,
						"y": 273,
						"w": 64,
						"h": 96
					},
					"anchor": {
						"x": 0.5,
						"y": 0.5
					}
				},
				{
					"filename": "attack-left-4.png",
					"rotated": false,
					"trimmed": false,
					"sourceSize": {
						"w": 72,
						"h": 88
					},
					"spriteSourceSize": {
						"x": 0,
						"y": 0,
						"w": 72,
						"h": 88
					},
					"frame": {
						"x": 467,
						"y": 87,
						"w": 72,
						"h": 88
					},
					"anchor": {
						"x": 0.5,
						"y": 0.5
					}
				},
				{
					"filename": "attack-down-2.png",
					"rotated": false,
					"trimmed": false,
					"sourceSize": {
						"w": 64,
						"h": 88
					},
					"spriteSourceSize": {
						"x": 0,
						"y": 0,
						"w": 64,
						"h": 88
					},
					"frame": {
						"x": 161,
						"y": 183,
						"w": 64,
						"h": 88
					},
					"anchor": {
						"x": 0.5,
						"y": 0.5
					}
				},
				{
					"filename": "carry-up-1.png",
					"rotated": false,
					"trimmed": false,
					"sourceSize": {
						"w": 64,
						"h": 92
					},
					"spriteSourceSize": {
						"x": 0,
						"y": 0,
						"w": 64,
						"h": 92
					},
					"frame": {
						"x": 133,
						"y": 273,
						"w": 64,
						"h": 92
					},
					"anchor": {
						"x": 0.5,
						"y": 0.5
					}
				},
				{
					"filename": "attack-up-1.png",
					"rotated": false,
					"trimmed": false,
					"sourceSize": {
						"w": 68,
						"h": 84
					},
					"spriteSourceSize": {
						"x": 0,
						"y": 0,
						"w": 68,
						"h": 84
					},
					"frame": {
						"x": 549,
						"y": 1,
						"w": 68,
						"h": 84
					},
					"anchor": {
						"x": 0.5,
						"y": 0.5
					}
				},
				{
					"filename": "carry-down-1.png",
					"rotated": false,
					"trimmed": false,
					"sourceSize": {
						"w": 64,
						"h": 88
					},
					"spriteSourceSize": {
						"x": 0,
						"y": 0,
						"w": 64,
						"h": 88
					},
					"frame": {
						"x": 541,
						"y": 87,
						"w": 64,
						"h": 88
					},
					"anchor": {
						"x": 0.5,
						"y": 0.5
					}
				},
				{
					"filename": "carry-down-3.png",
					"rotated": false,
					"trimmed": false,
					"sourceSize": {
						"w": 64,
						"h": 88
					},
					"spriteSourceSize": {
						"x": 0,
						"y": 0,
						"w": 64,
						"h": 88
					},
					"frame": {
						"x": 227,
						"y": 183,
						"w": 64,
						"h": 88
					},
					"anchor": {
						"x": 0.5,
						"y": 0.5
					}
				},
				{
					"filename": "carry-up-3.png",
					"rotated": false,
					"trimmed": false,
					"sourceSize": {
						"w": 64,
						"h": 92
					},
					"spriteSourceSize": {
						"x": 0,
						"y": 0,
						"w": 64,
						"h": 92
					},
					"frame": {
						"x": 199,
						"y": 273,
						"w": 64,
						"h": 92
					},
					"anchor": {
						"x": 0.5,
						"y": 0.5
					}
				},
				{
					"filename": "carry-up-2.png",
					"rotated": false,
					"trimmed": false,
					"sourceSize": {
						"w": 64,
						"h": 88
					},
					"spriteSourceSize": {
						"x": 0,
						"y": 0,
						"w": 64,
						"h": 88
					},
					"frame": {
						"x": 293,
						"y": 183,
						"w": 64,
						"h": 88
					},
					"anchor": {
						"x": 0.5,
						"y": 0.5
					}
				},
				{
					"filename": "carry-up-4.png",
					"rotated": false,
					"trimmed": false,
					"sourceSize": {
						"w": 64,
						"h": 88
					},
					"spriteSourceSize": {
						"x": 0,
						"y": 0,
						"w": 64,
						"h": 88
					},
					"frame": {
						"x": 265,
						"y": 273,
						"w": 64,
						"h": 88
					},
					"anchor": {
						"x": 0.5,
						"y": 0.5
					}
				},
				{
					"filename": "grab-down-3.png",
					"rotated": false,
					"trimmed": false,
					"sourceSize": {
						"w": 64,
						"h": 88
					},
					"spriteSourceSize": {
						"x": 0,
						"y": 0,
						"w": 64,
						"h": 88
					},
					"frame": {
						"x": 359,
						"y": 183,
						"w": 64,
						"h": 88
					},
					"anchor": {
						"x": 0.5,
						"y": 0.5
					}
				},
				{
					"filename": "grab-up-3.png",
					"rotated": false,
					"trimmed": false,
					"sourceSize": {
						"w": 64,
						"h": 88
					},
					"spriteSourceSize": {
						"x": 0,
						"y": 0,
						"w": 64,
						"h": 88
					},
					"frame": {
						"x": 331,
						"y": 273,
						"w": 64,
						"h": 88
					},
					"anchor": {
						"x": 0.5,
						"y": 0.5
					}
				},
				{
					"filename": "attack-down-1.png",
					"rotated": false,
					"trimmed": false,
					"sourceSize": {
						"w": 64,
						"h": 84
					},
					"spriteSourceSize": {
						"x": 0,
						"y": 0,
						"w": 64,
						"h": 84
					},
					"frame": {
						"x": 619,
						"y": 1,
						"w": 64,
						"h": 84
					},
					"anchor": {
						"x": 0.5,
						"y": 0.5
					}
				},
				{
					"filename": "attack-right-1.png",
					"rotated": false,
					"trimmed": false,
					"sourceSize": {
						"w": 64,
						"h": 84
					},
					"spriteSourceSize": {
						"x": 0,
						"y": 0,
						"w": 64,
						"h": 84
					},
					"frame": {
						"x": 607,
						"y": 87,
						"w": 64,
						"h": 84
					},
					"anchor": {
						"x": 0.5,
						"y": 0.5
					}
				},
				{
					"filename": "attack-up-2.png",
					"rotated": false,
					"trimmed": false,
					"sourceSize": {
						"w": 68,
						"h": 80
					},
					"spriteSourceSize": {
						"x": 0,
						"y": 0,
						"w": 68,
						"h": 80
					},
					"frame": {
						"x": 1,
						"y": 371,
						"w": 68,
						"h": 80
					},
					"anchor": {
						"x": 0.5,
						"y": 0.5
					}
				},
				{
					"filename": "carry-down-2.png",
					"rotated": false,
					"trimmed": false,
					"sourceSize": {
						"w": 64,
						"h": 84
					},
					"spriteSourceSize": {
						"x": 0,
						"y": 0,
						"w": 64,
						"h": 84
					},
					"frame": {
						"x": 685,
						"y": 1,
						"w": 64,
						"h": 84
					},
					"anchor": {
						"x": 0.5,
						"y": 0.5
					}
				},
				{
					"filename": "carry-down-4.png",
					"rotated": false,
					"trimmed": false,
					"sourceSize": {
						"w": 64,
						"h": 84
					},
					"spriteSourceSize": {
						"x": 0,
						"y": 0,
						"w": 64,
						"h": 84
					},
					"frame": {
						"x": 673,
						"y": 87,
						"w": 64,
						"h": 84
					},
					"anchor": {
						"x": 0.5,
						"y": 0.5
					}
				},
				{
					"filename": "attack-right-3.png",
					"rotated": false,
					"trimmed": false,
					"sourceSize": {
						"w": 60,
						"h": 88
					},
					"spriteSourceSize": {
						"x": 0,
						"y": 0,
						"w": 60,
						"h": 88
					},
					"frame": {
						"x": 751,
						"y": 1,
						"w": 60,
						"h": 88
					},
					"anchor": {
						"x": 0.5,
						"y": 0.5
					}
				},
				{
					"filename": "attack-right-4.png",
					"rotated": false,
					"trimmed": false,
					"sourceSize": {
						"w": 60,
						"h": 88
					},
					"spriteSourceSize": {
						"x": 0,
						"y": 0,
						"w": 60,
						"h": 88
					},
					"frame": {
						"x": 813,
						"y": 1,
						"w": 60,
						"h": 88
					},
					"anchor": {
						"x": 0.5,
						"y": 0.5
					}
				},
				{
					"filename": "attack-up-3.png",
					"rotated": false,
					"trimmed": false,
					"sourceSize": {
						"w": 60,
						"h": 88
					},
					"spriteSourceSize": {
						"x": 0,
						"y": 0,
						"w": 60,
						"h": 88
					},
					"frame": {
						"x": 875,
						"y": 1,
						"w": 60,
						"h": 88
					},
					"anchor": {
						"x": 0.5,
						"y": 0.5
					}
				},
				{
					"filename": "grab-down-1.png",
					"rotated": false,
					"trimmed": false,
					"sourceSize": {
						"w": 60,
						"h": 80
					},
					"spriteSourceSize": {
						"x": 0,
						"y": 0,
						"w": 60,
						"h": 80
					},
					"frame": {
						"x": 71,
						"y": 371,
						"w": 60,
						"h": 80
					},
					"anchor": {
						"x": 0.5,
						"y": 0.5
					}
				},
				{
					"filename": "grab-right-1.png",
					"rotated": false,
					"trimmed": false,
					"sourceSize": {
						"w": 64,
						"h": 80
					},
					"spriteSourceSize": {
						"x": 0,
						"y": 0,
						"w": 64,
						"h": 80
					},
					"frame": {
						"x": 133,
						"y": 367,
						"w": 64,
						"h": 80
					},
					"anchor": {
						"x": 0.5,
						"y": 0.5
					}
				},
				{
					"filename": "grab-left-1.png",
					"rotated": false,
					"trimmed": false,
					"sourceSize": {
						"w": 60,
						"h": 80
					},
					"spriteSourceSize": {
						"x": 0,
						"y": 0,
						"w": 60,
						"h": 80
					},
					"frame": {
						"x": 199,
						"y": 367,
						"w": 60,
						"h": 80
					},
					"anchor": {
						"x": 0.5,
						"y": 0.5
					}
				},
				{
					"filename": "attack-left-1.png",
					"rotated": false,
					"trimmed": false,
					"sourceSize": {
						"w": 52,
						"h": 88
					},
					"spriteSourceSize": {
						"x": 0,
						"y": 0,
						"w": 52,
						"h": 88
					},
					"frame": {
						"x": 425,
						"y": 183,
						"w": 52,
						"h": 88
					},
					"anchor": {
						"x": 0.5,
						"y": 0.5
					}
				},
				{
					"filename": "attack-up-4.png",
					"rotated": false,
					"trimmed": false,
					"sourceSize": {
						"w": 60,
						"h": 88
					},
					"spriteSourceSize": {
						"x": 0,
						"y": 0,
						"w": 60,
						"h": 88
					},
					"frame": {
						"x": 397,
						"y": 273,
						"w": 60,
						"h": 88
					},
					"anchor": {
						"x": 0.5,
						"y": 0.5
					}
				},
				{
					"filename": "walk-up-1.png",
					"rotated": false,
					"trimmed": false,
					"sourceSize": {
						"w": 60,
						"h": 92
					},
					"spriteSourceSize": {
						"x": 0,
						"y": 0,
						"w": 60,
						"h": 92
					},
					"frame": {
						"x": 479,
						"y": 177,
						"w": 60,
						"h": 92
					},
					"anchor": {
						"x": 0.5,
						"y": 0.5
					}
				},
				{
					"filename": "walk-up-3.png",
					"rotated": false,
					"trimmed": false,
					"sourceSize": {
						"w": 60,
						"h": 92
					},
					"spriteSourceSize": {
						"x": 0,
						"y": 0,
						"w": 60,
						"h": 92
					},
					"frame": {
						"x": 541,
						"y": 177,
						"w": 60,
						"h": 92
					},
					"anchor": {
						"x": 0.5,
						"y": 0.5
					}
				},
				{
					"filename": "die.png",
					"rotated": false,
					"trimmed": false,
					"sourceSize": {
						"w": 60,
						"h": 88
					},
					"spriteSourceSize": {
						"x": 0,
						"y": 0,
						"w": 60,
						"h": 88
					},
					"frame": {
						"x": 739,
						"y": 91,
						"w": 60,
						"h": 88
					},
					"anchor": {
						"x": 0.5,
						"y": 0.5
					}
				},
				{
					"filename": "grab-down-2.png",
					"rotated": false,
					"trimmed": false,
					"sourceSize": {
						"w": 60,
						"h": 88
					},
					"spriteSourceSize": {
						"x": 0,
						"y": 0,
						"w": 60,
						"h": 88
					},
					"frame": {
						"x": 801,
						"y": 91,
						"w": 60,
						"h": 88
					},
					"anchor": {
						"x": 0.5,
						"y": 0.5
					}
				},
				{
					"filename": "grab-up-2.png",
					"rotated": false,
					"trimmed": false,
					"sourceSize": {
						"w": 60,
						"h": 88
					},
					"spriteSourceSize": {
						"x": 0,
						"y": 0,
						"w": 60,
						"h": 88
					},
					"frame": {
						"x": 863,
						"y": 91,
						"w": 60,
						"h": 88
					},
					"anchor": {
						"x": 0.5,
						"y": 0.5
					}
				},
				{
					"filename": "carry-left-1.png",
					"rotated": false,
					"trimmed": false,
					"sourceSize": {
						"w": 52,
						"h": 88
					},
					"spriteSourceSize": {
						"x": 0,
						"y": 0,
						"w": 52,
						"h": 88
					},
					"frame": {
						"x": 459,
						"y": 273,
						"w": 52,
						"h": 88
					},
					"anchor": {
						"x": 0.5,
						"y": 0.5
					}
				},
				{
					"filename": "walk-down-1.png",
					"rotated": false,
					"trimmed": false,
					"sourceSize": {
						"w": 60,
						"h": 88
					},
					"spriteSourceSize": {
						"x": 0,
						"y": 0,
						"w": 60,
						"h": 88
					},
					"frame": {
						"x": 513,
						"y": 271,
						"w": 60,
						"h": 88
					},
					"anchor": {
						"x": 0.5,
						"y": 0.5
					}
				},
				{
					"filename": "carry-left-3.png",
					"rotated": false,
					"trimmed": false,
					"sourceSize": {
						"w": 52,
						"h": 88
					},
					"spriteSourceSize": {
						"x": 0,
						"y": 0,
						"w": 52,
						"h": 88
					},
					"frame": {
						"x": 575,
						"y": 271,
						"w": 52,
						"h": 88
					},
					"anchor": {
						"x": 0.5,
						"y": 0.5
					}
				},
				{
					"filename": "carry-right-1.png",
					"rotated": false,
					"trimmed": false,
					"sourceSize": {
						"w": 56,
						"h": 88
					},
					"spriteSourceSize": {
						"x": 0,
						"y": 0,
						"w": 56,
						"h": 88
					},
					"frame": {
						"x": 603,
						"y": 181,
						"w": 56,
						"h": 88
					},
					"anchor": {
						"x": 0.5,
						"y": 0.5
					}
				},
				{
					"filename": "walk-down-3.png",
					"rotated": false,
					"trimmed": false,
					"sourceSize": {
						"w": 60,
						"h": 88
					},
					"spriteSourceSize": {
						"x": 0,
						"y": 0,
						"w": 60,
						"h": 88
					},
					"frame": {
						"x": 661,
						"y": 173,
						"w": 60,
						"h": 88
					},
					"anchor": {
						"x": 0.5,
						"y": 0.5
					}
				},
				{
					"filename": "grab-up-1.png",
					"rotated": false,
					"trimmed": false,
					"sourceSize": {
						"w": 60,
						"h": 80
					},
					"spriteSourceSize": {
						"x": 0,
						"y": 0,
						"w": 60,
						"h": 80
					},
					"frame": {
						"x": 723,
						"y": 181,
						"w": 60,
						"h": 80
					},
					"anchor": {
						"x": 0.5,
						"y": 0.5
					}
				},
				{
					"filename": "walk-down-2.png",
					"rotated": false,
					"trimmed": false,
					"sourceSize": {
						"w": 60,
						"h": 84
					},
					"spriteSourceSize": {
						"x": 0,
						"y": 0,
						"w": 60,
						"h": 84
					},
					"frame": {
						"x": 785,
						"y": 181,
						"w": 60,
						"h": 84
					},
					"anchor": {
						"x": 0.5,
						"y": 0.5
					}
				},
				{
					"filename": "walk-down-4.png",
					"rotated": false,
					"trimmed": false,
					"sourceSize": {
						"w": 60,
						"h": 84
					},
					"spriteSourceSize": {
						"x": 0,
						"y": 0,
						"w": 60,
						"h": 84
					},
					"frame": {
						"x": 847,
						"y": 181,
						"w": 60,
						"h": 84
					},
					"anchor": {
						"x": 0.5,
						"y": 0.5
					}
				},
				{
					"filename": "grab-left-2.png",
					"rotated": false,
					"trimmed": false,
					"sourceSize": {
						"w": 52,
						"h": 88
					},
					"spriteSourceSize": {
						"x": 0,
						"y": 0,
						"w": 52,
						"h": 88
					},
					"frame": {
						"x": 909,
						"y": 181,
						"w": 52,
						"h": 88
					},
					"anchor": {
						"x": 0.5,
						"y": 0.5
					}
				},
				{
					"filename": "carry-right-3.png",
					"rotated": false,
					"trimmed": false,
					"sourceSize": {
						"w": 56,
						"h": 88
					},
					"spriteSourceSize": {
						"x": 0,
						"y": 0,
						"w": 56,
						"h": 88
					},
					"frame": {
						"x": 629,
						"y": 271,
						"w": 56,
						"h": 88
					},
					"anchor": {
						"x": 0.5,
						"y": 0.5
					}
				},
				{
					"filename": "walk-up-2.png",
					"rotated": false,
					"trimmed": false,
					"sourceSize": {
						"w": 60,
						"h": 88
					},
					"spriteSourceSize": {
						"x": 0,
						"y": 0,
						"w": 60,
						"h": 88
					},
					"frame": {
						"x": 687,
						"y": 263,
						"w": 60,
						"h": 88
					},
					"anchor": {
						"x": 0.5,
						"y": 0.5
					}
				},
				{
					"filename": "walk-up-4.png",
					"rotated": false,
					"trimmed": false,
					"sourceSize": {
						"w": 60,
						"h": 88
					},
					"spriteSourceSize": {
						"x": 0,
						"y": 0,
						"w": 60,
						"h": 88
					},
					"frame": {
						"x": 749,
						"y": 267,
						"w": 60,
						"h": 88
					},
					"anchor": {
						"x": 0.5,
						"y": 0.5
					}
				},
				{
					"filename": "carry-right-2.png",
					"rotated": false,
					"trimmed": false,
					"sourceSize": {
						"w": 56,
						"h": 84
					},
					"spriteSourceSize": {
						"x": 0,
						"y": 0,
						"w": 56,
						"h": 84
					},
					"frame": {
						"x": 811,
						"y": 267,
						"w": 56,
						"h": 84
					},
					"anchor": {
						"x": 0.5,
						"y": 0.5
					}
				},
				{
					"filename": "carry-right-4.png",
					"rotated": false,
					"trimmed": false,
					"sourceSize": {
						"w": 56,
						"h": 84
					},
					"spriteSourceSize": {
						"x": 0,
						"y": 0,
						"w": 56,
						"h": 84
					},
					"frame": {
						"x": 869,
						"y": 271,
						"w": 56,
						"h": 84
					},
					"anchor": {
						"x": 0.5,
						"y": 0.5
					}
				},
				{
					"filename": "carry-left-2.png",
					"rotated": false,
					"trimmed": false,
					"sourceSize": {
						"w": 52,
						"h": 84
					},
					"spriteSourceSize": {
						"x": 0,
						"y": 0,
						"w": 52,
						"h": 84
					},
					"frame": {
						"x": 261,
						"y": 367,
						"w": 52,
						"h": 84
					},
					"anchor": {
						"x": 0.5,
						"y": 0.5
					}
				},
				{
					"filename": "grab-left-3.png",
					"rotated": false,
					"trimmed": false,
					"sourceSize": {
						"w": 52,
						"h": 88
					},
					"spriteSourceSize": {
						"x": 0,
						"y": 0,
						"w": 52,
						"h": 88
					},
					"frame": {
						"x": 315,
						"y": 363,
						"w": 52,
						"h": 88
					},
					"anchor": {
						"x": 0.5,
						"y": 0.5
					}
				},
				{
					"filename": "grab-right-2.png",
					"rotated": false,
					"trimmed": false,
					"sourceSize": {
						"w": 52,
						"h": 88
					},
					"spriteSourceSize": {
						"x": 0,
						"y": 0,
						"w": 52,
						"h": 88
					},
					"frame": {
						"x": 369,
						"y": 363,
						"w": 52,
						"h": 88
					},
					"anchor": {
						"x": 0.5,
						"y": 0.5
					}
				},
				{
					"filename": "grab-right-3.png",
					"rotated": false,
					"trimmed": false,
					"sourceSize": {
						"w": 52,
						"h": 88
					},
					"spriteSourceSize": {
						"x": 0,
						"y": 0,
						"w": 52,
						"h": 88
					},
					"frame": {
						"x": 423,
						"y": 363,
						"w": 52,
						"h": 88
					},
					"anchor": {
						"x": 0.5,
						"y": 0.5
					}
				},
				{
					"filename": "walk-left-1.png",
					"rotated": false,
					"trimmed": false,
					"sourceSize": {
						"w": 52,
						"h": 88
					},
					"spriteSourceSize": {
						"x": 0,
						"y": 0,
						"w": 52,
						"h": 88
					},
					"frame": {
						"x": 477,
						"y": 363,
						"w": 52,
						"h": 88
					},
					"anchor": {
						"x": 0.5,
						"y": 0.5
					}
				},
				{
					"filename": "walk-left-3.png",
					"rotated": false,
					"trimmed": false,
					"sourceSize": {
						"w": 52,
						"h": 88
					},
					"spriteSourceSize": {
						"x": 0,
						"y": 0,
						"w": 52,
						"h": 88
					},
					"frame": {
						"x": 531,
						"y": 361,
						"w": 52,
						"h": 88
					},
					"anchor": {
						"x": 0.5,
						"y": 0.5
					}
				},
				{
					"filename": "walk-right-1.png",
					"rotated": false,
					"trimmed": false,
					"sourceSize": {
						"w": 52,
						"h": 88
					},
					"spriteSourceSize": {
						"x": 0,
						"y": 0,
						"w": 52,
						"h": 88
					},
					"frame": {
						"x": 585,
						"y": 361,
						"w": 52,
						"h": 88
					},
					"anchor": {
						"x": 0.5,
						"y": 0.5
					}
				},
				{
					"filename": "walk-right-3.png",
					"rotated": false,
					"trimmed": false,
					"sourceSize": {
						"w": 52,
						"h": 88
					},
					"spriteSourceSize": {
						"x": 0,
						"y": 0,
						"w": 52,
						"h": 88
					},
					"frame": {
						"x": 639,
						"y": 361,
						"w": 52,
						"h": 88
					},
					"anchor": {
						"x": 0.5,
						"y": 0.5
					}
				},
				{
					"filename": "carry-left-4.png",
					"rotated": false,
					"trimmed": false,
					"sourceSize": {
						"w": 52,
						"h": 84
					},
					"spriteSourceSize": {
						"x": 0,
						"y": 0,
						"w": 52,
						"h": 84
					},
					"frame": {
						"x": 693,
						"y": 353,
						"w": 52,
						"h": 84
					},
					"anchor": {
						"x": 0.5,
						"y": 0.5
					}
				},
				{
					"filename": "walk-left-2.png",
					"rotated": false,
					"trimmed": false,
					"sourceSize": {
						"w": 52,
						"h": 84
					},
					"spriteSourceSize": {
						"x": 0,
						"y": 0,
						"w": 52,
						"h": 84
					},
					"frame": {
						"x": 747,
						"y": 357,
						"w": 52,
						"h": 84
					},
					"anchor": {
						"x": 0.5,
						"y": 0.5
					}
				},
				{
					"filename": "walk-left-4.png",
					"rotated": false,
					"trimmed": false,
					"sourceSize": {
						"w": 52,
						"h": 84
					},
					"spriteSourceSize": {
						"x": 0,
						"y": 0,
						"w": 52,
						"h": 84
					},
					"frame": {
						"x": 801,
						"y": 357,
						"w": 52,
						"h": 84
					},
					"anchor": {
						"x": 0.5,
						"y": 0.5
					}
				},
				{
					"filename": "walk-right-2.png",
					"rotated": false,
					"trimmed": false,
					"sourceSize": {
						"w": 52,
						"h": 84
					},
					"spriteSourceSize": {
						"x": 0,
						"y": 0,
						"w": 52,
						"h": 84
					},
					"frame": {
						"x": 855,
						"y": 357,
						"w": 52,
						"h": 84
					},
					"anchor": {
						"x": 0.5,
						"y": 0.5
					}
				},
				{
					"filename": "walk-right-4.png",
					"rotated": false,
					"trimmed": false,
					"sourceSize": {
						"w": 52,
						"h": 84
					},
					"spriteSourceSize": {
						"x": 0,
						"y": 0,
						"w": 52,
						"h": 84
					},
					"frame": {
						"x": 909,
						"y": 357,
						"w": 52,
						"h": 84
					},
					"anchor": {
						"x": 0.5,
						"y": 0.5
					}
				}
			]
		}
	],
	"meta": {
		"app": "https://www.codeandweb.com/texturepacker",
		"version": "3.0",
		"smartupdate": "$TexturePacker:SmartUpdate:731fa10f9ec2d9bd8c152852dee3c906:701bff86a79fa65a11aedf3f22f313a8:42e475aa4a03af306bdc7acb5ff91d19$"
	}
}
